{"graphs": [{"id": "175163408222972", "nodes": [{"name": "ibuf", "id": "node_17516340822234", "instanceName": "ip_ibuf", "twoColumn": true, "interfaces": [{"name": "a", "id": "ni_17516340822230", "direction": "input", "side": "left"}, {"name": "clk", "id": "ni_17516340822231", "direction": "input", "side": "left"}, {"name": "rst", "id": "ni_17516340822232", "direction": "input", "side": "left"}, {"name": "z", "id": "ni_17516340822233", "direction": "output", "side": "right"}], "properties": []}, {"name": "obuf", "id": "node_175163408222410", "instanceName": "ip_obuf", "twoColumn": true, "interfaces": [{"name": "a", "id": "ni_17516340822245", "direction": "input", "side": "left"}, {"name": "clk", "id": "ni_17516340822246", "direction": "input", "side": "left"}, {"name": "oe", "id": "ni_17516340822247", "direction": "input", "side": "left"}, {"name": "rst", "id": "ni_17516340822248", "direction": "input", "side": "left"}, {"name": "z", "id": "ni_17516340822249", "direction": "output", "side": "right"}], "properties": []}, {"name": "iobuf", "id": "node_175163408222517", "instanceName": "ip_iobuf", "twoColumn": true, "interfaces": [{"name": "a", "id": "ni_175163408222511", "direction": "input", "side": "left"}, {"name": "clk", "id": "ni_175163408222512", "direction": "input", "side": "left"}, {"name": "oe", "id": "ni_175163408222513", "direction": "input", "side": "left"}, {"name": "rst", "id": "ni_175163408222514", "direction": "input", "side": "left"}, {"name": "y", "id": "ni_175163408222515", "direction": "output", "side": "right"}, {"name": "z", "id": "ni_175163408222516", "direction": "inout", "side": "right"}], "properties": []}, {"name": "External Input", "id": "node_175163408222520", "instanceName": "External Input", "twoColumn": true, "interfaces": [{"name": "external", "id": "ni_175163408222519", "direction": "output", "side": "right"}], "properties": [{"name": "External Name", "id": "175163408222518", "value": "PORT_CLK"}]}, {"name": "External Input", "id": "node_175163408222523", "instanceName": "External Input", "twoColumn": true, "interfaces": [{"name": "external", "id": "ni_175163408222522", "direction": "output", "side": "right"}], "properties": [{"name": "External Name", "id": "175163408222521", "value": "PORT_RST"}]}, {"name": "External Input", "id": "node_175163408222526", "instanceName": "External Input", "twoColumn": true, "interfaces": [{"name": "external", "id": "ni_175163408222525", "direction": "output", "side": "right"}], "properties": [{"name": "External Name", "id": "175163408222524", "value": "PORT_IN"}]}, {"name": "External Output", "id": "node_175163408222529", "instanceName": "External Output", "twoColumn": true, "interfaces": [{"name": "external", "id": "ni_175163408222528", "direction": "input", "side": "left"}], "properties": [{"name": "External Name", "id": "175163408222527", "value": "PORT_OUT_0"}]}, {"name": "External Output", "id": "node_175163408222532", "instanceName": "External Output", "twoColumn": true, "interfaces": [{"name": "external", "id": "ni_175163408222531", "direction": "input", "side": "left"}], "properties": [{"name": "External Name", "id": "175163408222530", "value": "PORT_OUT_1"}]}, {"name": "External Output", "id": "node_175163408222535", "instanceName": "External Output", "twoColumn": true, "interfaces": [{"name": "external", "id": "ni_175163408222534", "direction": "input", "side": "left"}], "properties": [{"name": "External Name", "id": "175163408222533", "value": "PORT_OUT_2"}]}, {"name": "External Inout", "id": "node_175163408222538", "instanceName": "External Inout", "twoColumn": true, "interfaces": [{"name": "external", "id": "ni_175163408222537", "direction": "inout", "side": "right"}], "properties": [{"name": "External Name", "id": "175163408222536", "value": "z"}]}], "connections": [{"id": "175163408222957", "from": "ni_175163408222519", "to": "ni_17516340822246"}, {"id": "175163408222958", "from": "ni_175163408222522", "to": "ni_17516340822248"}, {"id": "175163408222959", "from": "ni_175163408222519", "to": "ni_17516340822247"}, {"id": "175163408222960", "from": "ni_175163408222525", "to": "ni_17516340822245"}, {"id": "175163408222961", "from": "ni_17516340822249", "to": "ni_175163408222528"}, {"id": "175163408222962", "from": "ni_175163408222519", "to": "ni_175163408222512"}, {"id": "175163408222963", "from": "ni_175163408222522", "to": "ni_175163408222514"}, {"id": "175163408222964", "from": "ni_175163408222519", "to": "ni_175163408222513"}, {"id": "175163408222965", "from": "ni_175163408222525", "to": "ni_175163408222511"}, {"id": "175163408222966", "from": "ni_175163408222515", "to": "ni_175163408222531"}, {"id": "175163408222967", "from": "ni_175163408222519", "to": "ni_17516340822231"}, {"id": "175163408222968", "from": "ni_175163408222522", "to": "ni_17516340822232"}, {"id": "175163408222969", "from": "ni_175163408222525", "to": "ni_17516340822230"}, {"id": "175163408222970", "from": "ni_17516340822233", "to": "ni_175163408222534"}, {"id": "175163408222971", "from": "ni_175163408222537", "to": "ni_175163408222516"}]}], "entryGraph": "175163408222972", "version": "20240723.13"}