{"graphs": [{"id": "174025841838639", "nodes": [{"name": "axis_streamer", "id": "node_17402584183773", "instanceName": "streamer", "twoColumn": true, "interfaces": [{"name": "clk", "id": "ni_17402584183770", "direction": "input", "side": "left"}, {"name": "io", "id": "ni_17402584183771", "direction": "output", "side": "right"}, {"name": "rst", "id": "ni_17402584183772", "direction": "input", "side": "left"}], "properties": []}, {"name": "axis_receiver", "id": "node_17402584183809", "instanceName": "receiver", "twoColumn": true, "interfaces": [{"name": "clk", "id": "ni_17402584183804", "direction": "input", "side": "left"}, {"name": "ext", "id": "ni_17402584183805", "direction": "inout", "side": "right"}, {"name": "io", "id": "ni_17402584183806", "direction": "input", "side": "left"}, {"name": "noise", "id": "ni_17402584183807", "direction": "input", "side": "left"}, {"name": "rst", "id": "ni_17402584183808", "direction": "input", "side": "left"}], "properties": []}, {"name": "External Input", "id": "node_174025841838012", "instanceName": "External Input", "twoColumn": true, "interfaces": [{"name": "external", "id": "ni_174025841838011", "direction": "output", "side": "right"}], "properties": [{"name": "External Name", "id": "174025841838010", "value": "clk"}]}, {"name": "External Input", "id": "node_174025841838015", "instanceName": "External Input", "twoColumn": true, "interfaces": [{"name": "external", "id": "ni_174025841838014", "direction": "output", "side": "right"}], "properties": [{"name": "External Name", "id": "174025841838013", "value": "rst"}]}, {"name": "External Inout", "id": "node_174025841838018", "instanceName": "External Inout", "twoColumn": true, "interfaces": [{"name": "external", "id": "ni_174025841838017", "direction": "inout", "side": "right"}], "properties": [{"name": "External Name", "id": "174025841838016", "value": "ext"}]}, {"name": "Constant", "id": "node_174025841838631", "instanceName": "Constant", "twoColumn": true, "interfaces": [{"name": "constant", "id": "ni_174025841838630", "direction": "output", "side": "right"}], "properties": [{"name": "Constant Value", "id": "174025841838629", "value": "2888"}]}], "connections": [{"id": "174025841838632", "from": "ni_17402584183771", "to": "ni_17402584183806"}, {"id": "174025841838633", "from": "ni_174025841838011", "to": "ni_17402584183770"}, {"id": "174025841838634", "from": "ni_174025841838014", "to": "ni_17402584183772"}, {"id": "174025841838635", "from": "ni_174025841838011", "to": "ni_17402584183804"}, {"id": "174025841838636", "from": "ni_174025841838014", "to": "ni_17402584183808"}, {"id": "174025841838637", "from": "ni_174025841838630", "to": "ni_17402584183807"}, {"id": "174025841838638", "from": "ni_174025841838017", "to": "ni_17402584183805"}]}], "entryGraph": "174025841838639", "version": "20240723.13"}